setup.py
nameko_dev/__init__.py
nameko_dev/autoreload.py
nameko_dev/commands.py
nameko_dev/main.py
nameko_dev/run.py
nameko_dev.egg-info/PKG-INFO
nameko_dev.egg-info/SOURCES.txt
nameko_dev.egg-info/dependency_links.txt
nameko_dev.egg-info/entry_points.txt
nameko_dev.egg-info/requires.txt
nameko_dev.egg-info/top_level.txt
nameko_dev.egg-info/zip-safe